README.md
setup.py
homedepot_search_results_scraper/__init__.py
homedepot_search_results_scraper.egg-info/PKG-INFO
homedepot_search_results_scraper.egg-info/SOURCES.txt
homedepot_search_results_scraper.egg-info/dependency_links.txt
homedepot_search_results_scraper.egg-info/requires.txt
homedepot_search_results_scraper.egg-info/top_level.txt